aids/__init__.py
aids/__main__.py
aids/commands.py
aids/help.txt
aids/manage.py
aids/to_html.py
aids/app/__init__.py
aids/app/client.py
aids/app/models.py
aids/app/obfuscate.py
aids/app/schemes.py
aids/app/settings.py
aids/app/tests.py
aids/app/writelogs.py
aids/app/test_files/Family.json
aids/app/test_files/The_Layover.scenario
aids/app/test_files/test_scen.json
aids/app/test_files/test_stories.json
aids/app/test_files/scenarios/style.css
aids/app/test_files/scenarios/Bloody Playground/style.css
aids/app/test_files/scenarios/Family Matters/style.css
aids/app/test_files/scenarios/Family Matters/Cousin/style.css
aids/app/test_files/scenarios/Family Matters/Mom/style.css
aids/app/test_files/scenarios/Family Matters/Sister/style.css
aids/app/test_files/scenarios/Fight In The Mud/style.css
aids/app/test_files/scenarios/Mom/style.css
aids/app/test_files/scenarios/Sister/style.css
aids/app/test_files/scenarios/Sleep Sex/style.css
aids/app/test_files/scenarios/Testing Suite/style.css
aids/app/test_files/scenarios/💔 A.I. Dungeon's Fortune Teller 💰/style.css
aids/app/test_files/stories/style.css
aids/static/style.css
aids/templates/.base.html.swp
aids/templates/.base.html.un~
aids/templates/base.html
aids/templates/base.html~
aids/templates/index.html
aids/templates/scenario.html
aids/templates/story.html
aids-0.2.2.data/scripts/aids
aids-0.2.2.data/scripts/aids-windows.bat
aids-0.2.2.dist-info/LICENSE
aids-0.2.2.dist-info/METADATA
aids-0.2.2.dist-info/WHEEL
aids-0.2.2.dist-info/top_level.txt
aids-0.2.2.dist-info/RECORD
