Metadata-Version: 2.1
Name: aids
Version: 0.2.2
Summary: Client for AI Dynamic Storytelling Services.
Home-page: https://github.com/Moist-Cat/AIDScrapper
Author: Moist-Cat
Author-email: moistanonpy@gmail.com
License: UNKNOWN
Platform: UNKNOWN
Classifier: Programming Language :: Python :: 3
Classifier: License :: OSI Approved :: MIT License
Classifier: Operating System :: OS Independent
Requires-Python: >=3.8
License-File: LICENSE
Requires-Dist: requests
Requires-Dist: jinja2
Requires-Dist: bs4
Requires-Dist: html5lib
